ditto/__init__.py
pyditto-0.1.3.dist-info/LICENSE
pyditto-0.1.3.dist-info/METADATA
pyditto-0.1.3.dist-info/WHEEL
pyditto-0.1.3.dist-info/RECORD
